shpy/__init__.py
shpy/integrate_shell.py
shpy/shellpy.py
shpy/shpy.py
shpy-1.data/scripts/shpy.bat
shpy-1.dist-info/METADATA
shpy-1.dist-info/RECORD
shpy-1.dist-info/WHEEL
shpy-1.dist-info/top_level.txt
