Metadata-Version: 2.1
Name: shpy
Version: 1
Summary: Make your shell python supportive.
Home-page: https://ZviWex.com
Author: ZviWex.
Author-email: zvikizviki@gmail.com
License: GNU
Platform: UNKNOWN
Classifier: Programming Language :: Python :: 2
Classifier: Operating System :: OS Independent
Requires-Python: ~=2.7
Requires-Dist: ipython
